sqlcli/__init__.py
sqlcli/__main__.py
sqlcli/_console.py
sqlcli/_demo/data.py
sqlcli/_demo/models.py
sqlcli/_help.py
sqlcli/_utils.py
sqlcli/main.py
sqlcli-0.1.0.dist-info/entry_points.txt
sqlcli-0.1.0.dist-info/LICENSE
sqlcli-0.1.0.dist-info/WHEEL
sqlcli-0.1.0.dist-info/METADATA
sqlcli-0.1.0.dist-info/RECORD
