Metadata-Version: 2.1
Name: sqlcli
Version: 0.1.0
Summary: A command line interface (CLI) for interacting with SQLModel.
Home-page: https://github.com/SamEdwardes/sqlcli
License: MIT
Keywords: sql,cli,typer,python,sqlmodel,rich,sqlalchemy
Author: SamEdwardes
Author-email: edwardes.s@gmail.com
Requires-Python: >=3.9,<4.0
Classifier: License :: OSI Approved :: MIT License
Classifier: Programming Language :: Python :: 3
Classifier: Programming Language :: Python :: 3.10
Classifier: Programming Language :: Python :: 3.9
Requires-Dist: rich (>=11.0.0,<12.0.0)
Requires-Dist: sqlmodel (>=0.0.6,<0.0.7)
Requires-Dist: typer (>=0.4.0,<0.5.0)
Project-URL: Documentation, https://samedwardes.github.io/sqlcli/
Project-URL: Repository, https://github.com/SamEdwardes/sqlcli
